sdepy/__init__.py
sdepy/_config.py
sdepy/analytical.py
sdepy/infrastructure.py
sdepy/integration.py
sdepy/kfun.py
sdepy/shortcuts.py
sdepy/tests/__init__.py
sdepy/tests/_pytest.ini
sdepy/tests/shared.py
sdepy/tests/test_analytical.py
sdepy/tests/test_integrator.py
sdepy/tests/test_kfunc.py
sdepy/tests/test_montecarlo.py
sdepy/tests/test_process.py
sdepy/tests/test_processes.py
sdepy/tests/test_quant.py
sdepy/tests/test_source.py
sdepy/tests/cfr/distr_err_expected.txt
sdepy/tests/cfr/histogram_err_expected.txt
sdepy/tests/cfr/params2_err_expected.txt
sdepy/tests/cfr/params5_err_expected.txt
sdepy/tests/cfr/quant2_err_expected.txt
sdepy/tests/cfr/quant5_err_expected.txt
sdepy-1.2.0.dist-info/LICENSE.txt
sdepy-1.2.0.dist-info/METADATA
sdepy-1.2.0.dist-info/WHEEL
sdepy-1.2.0.dist-info/top_level.txt
sdepy-1.2.0.dist-info/RECORD
