Metadata-Version: 2.1
Name: sdepy
Version: 1.2.0
Summary: SdePy: Numerical Integration of Ito Stochastic Differential Equations
Home-page: https://github.com/sdepy/sdepy
Author: Maurizio Cipollina
Author-email: sdepydev@gmail.com
License: BSD
Download-URL: https://pypi.org/project/sdepy
Platform: Windows
Platform: Linux
Platform: Solaris
Platform: Mac OS-X
Platform: Unix
Classifier: Development Status :: 4 - Beta
Classifier: Intended Audience :: Science/Research
Classifier: Intended Audience :: Developers
Classifier: License :: OSI Approved :: BSD License
Classifier: Programming Language :: Python
Classifier: Programming Language :: Python :: 3 :: Only
Classifier: Programming Language :: Python :: 3
Classifier: Programming Language :: Python :: 3.6
Classifier: Programming Language :: Python :: 3.7
Classifier: Programming Language :: Python :: 3.8
Classifier: Programming Language :: Python :: 3.9
Classifier: Topic :: Software Development
Classifier: Topic :: Scientific/Engineering
Classifier: Operating System :: OS Independent
Requires-Python: >=3.6
Requires-Dist: numpy (>=1.15.2)
Requires-Dist: scipy (>=0.19.1)
